numjuggler/__init__.py
numjuggler/__main__.py
numjuggler/fmesh.py
numjuggler/likefunc.py
numjuggler/main.py
numjuggler/mapparsers.py
numjuggler/nogq.py
numjuggler/nogq2.py
numjuggler/numbering.py
numjuggler/parser.py
numjuggler/ri_notation.py
numjuggler/shortener.py
numjuggler/splitter.py
numjuggler/string_cells.py
numjuggler/version.py
numjuggler/utils/PartialFormatter.py
numjuggler/utils/__init__.py
numjuggler/utils/io.py
numjuggler/utils/resource.py
numjuggler-2.42.37.dist-info/LICENSE
numjuggler-2.42.37.dist-info/METADATA
numjuggler-2.42.37.dist-info/WHEEL
numjuggler-2.42.37.dist-info/entry_points.txt
numjuggler-2.42.37.dist-info/top_level.txt
numjuggler-2.42.37.dist-info/RECORD
