Metadata-Version: 2.2
Name: numjuggler
Version: 2.42.37
Summary: MCNP input file renumbering tool
Home-page: https://numjuggler.readthedocs.io
Author: A.Travleev
Author-email: anton.travleev@gmail.com
Keywords: MCNP,ITER,PARSER,RENUMBER
Classifier: Development Status :: 4 - Beta
Classifier: Environment :: Console
Classifier: Intended Audience :: Science/Research
Classifier: Intended Audience :: Education
Classifier: License :: OSI Approved :: GNU General Public License v3 (GPLv3)
Classifier: Programming Language :: Python :: 2.7
Classifier: Programming Language :: Python :: 3.7
Classifier: Programming Language :: Python :: 3.13
Classifier: Topic :: Utilities
License-File: LICENSE
Requires-Dist: six
Requires-Dist: pathlib2
Requires-Dist: chardet
Dynamic: author
Dynamic: author-email
Dynamic: classifier
Dynamic: description
Dynamic: description-content-type
Dynamic: home-page
Dynamic: keywords
Dynamic: requires-dist
Dynamic: summary
